{
    "choose_institute": "Kies een instituut",
    "logout": "Afmelden",
    "search_a_client": "Zoek een klant",
    "my_customers": "Mijn klanten",
    "my_visits": "Mijn bezoeken",
    "care_protocoles": "Protocollen van zorg",
    "my_protocols": "Mijn protocollen",
    "new_protocols": "Nieuw protocol",
    "my_products": "Mijn producten",
    "my_quotes": "Mijn offertes",
    "my_invoices": "Mijn facturen",
    "my_prices": "Mijn tarieven",
    "objets": "Objecten",
    "technologies": "Technologieën",
    "anamnesis": "Geschiedenissen",
    "feedback": "Terugkoppeling",
    "emails": "E-mails",
    "release": "Stortplaatsen",
    "post_processing": "Postverwerking",
    "protocol_tags": "Protocol tags",
    "institutes": "instituties",
    "all_institutes": "Alle instituten",
    "new_institute": "Nieuw instituut",
    "general_conditions": "Voorwaarden",
    "users": "Gebruikers",
    "all_users": "Alle gebruikers",
    "new_user": "Nieuwe gebruiker",
    "statistics": "statistiek",
    "the_customers": "Klanten",
    "delete": "Verwijderen",
    "question": "Vraag",
    "questions": "Vragen",
    "filter_one_col": "Filter op een kolom",
    "anamanese_subtitle": "Zoek de anamnese van protocollen",
    "new_anamanese_name": "Naam van de nieuwe anamnese",
    "new_anamanese": "Nieuwe anamnese",
    "name_of_new_protocol": "Naam van het nieuwe protocol",
    "name": "Naam",
    "firstname": "Voornaam",
    "tel_number": "Telefoonnummer",
    "informations": "informatie",
    "health": "gezondheid",
    "mailing": "mailing",
    "#": "#",
    "address": "adres",
    "ZIP": "Postcode",
    "town": "Gemeenschap",
    "country": "land",
    "website": "website",
    "url_meeting_page": "Url van het maken van een afspraak",
    "email_address": "E-mailadres",
    "GSM": "GSM",
    "birthdate": "Geboortedatum",
    "sexe": "soort",
    "man": "man",
    "woman": "vrouw",
    "institute": "Centrum / Instituut",
    "save": "redden",
    "profil_created_on": "Profiel gemaakt op",
    "smoking": "roken",
    "medical_background": "Medische geschiedenis *",
    "drugs_price": "Drugs prijs",
    "upsell": "upsell",
    "upsell_infos": "Ontvangt promotionele e-mails zoals gedefinieerd in het behandelprotocolelement",
    "info_treatment": "Informatie behandelingen",
    "info_treatment_infos": "Ontvangt informatie over verschillende producten",
    "cure_rapel": "Herinneringen genezen",
    "cure_rapell_infos": "Ontvangt herinneringen om volgende afspraken te maken (vastgelegd in protocol)",
    "treatments_information": "Informatie behandelingen",
    "receives_information_about_different_products": "Ontvangt informatie over verschillende producten",
    "reminders_cure": "Herinneringen genezen",
    "receives_reminders_to_make_next_appointments": "Ontvangt herinneringen om volgende afspraken te maken (vastgelegd in protocol)",
    "dated": "datum",
    "hour": "tijd",
    "treatment": "behandeling",
    "the_visits": "bezoeken",
    "all_the_visits": "Alle bezoeken aan de show",
    "client_name": "Klant Naam",
    "first_name": "Voornaam",
    "center": "centrum",
    "information": "informatie",
    "discharge": "ontlading",
    "client_sign": "Handtekening van de klant",
    "anamnese": "anamnese",
    "feed_back_post_care": "Voer postzorg terug",
    "in_case_of_answer_yes": "In het geval van een &quot;Ja&quot; -antwoord kan verdere verwerking niet plaatsvinden",
    "photo": "foto",
    "my_care_protocols": "My Care-protocollen",
    "find_the_celestetic_protocols_and_yours": "Zoek de protocollen van Celestetic en de jouwe. Let op, u moet de zorgprotocollen in het profiel van het instituut activeren om ze te associëren.",
    "login": "login",
    "password": "wachtwoord",
    "password_confirm": "Bevestiging van wachtwoord",
    "credentials_create": "Creëer de inloggegevens",
    "credentials_save": "Inloggegevens opslaan",
    "yes": "ja",
    "new_password": "Nieuw wachtwoord",
    "protocol_name": "Protocol naam",
    "number_of_sessions": "Aantal sessies",
    "description": "Beschrijving",
    "treatments": "behandelingen",
    "benefits": "voordelen",
    "here_benefits": "Geef hier de voordelen van de behandeling aan",
    "post_processing_protocol": "Post Processing Protocol",
    "feedback_questionnaire": "Feedback vragenlijst",
    "feminder_emails_and_post": "Herinnerings-e-mails en Post-upsell / cross-sell-verwerking",
    "presession_photos": "Pre-sessie foto&#39;s",
    "postsession_photos": "Foto&#39;s na de sessie",
    "cosmetics_recommended_for_this_protocol": "Cosmetica aanbevolen voor dit protocol",
    "some_lines_of_text": "Sommige tekstregels",
    "variants": "varianten",
    "insert_variants": "Voeg varianten en link-technologieën toe aan elke variant",
    "variant": "variant",
    "add_variation": "Voeg een variatie toe",
    "add": "toevoegen",
    "create_this_new_protocol": "Maak dit nieuwe protocol",
    "name_of_the_new_protocol": "Naam van het nieuwe protocol",
    "quotation": "citaat",
    "quotes_made_by_institute": "De citaten gemaakt door de show",
    "invoices": "facturen",
    "invoices_made_by_institute": "Facturen gemaakt door de show",
    "id": "id",
    "questionnaire_name": "Naam van de vragenlijst",
    "creation_date": "Aanmaakdatum",
    "customer_ref": "Klant Ref",
    "customer": "klant",
    "total": "totaal",
    "quotation_no": "Citaat nr",
    "date": "datum",
    "print": "printen",
    "sent": "verzonden",
    "send": "sturen",
    "quantity": "hoeveelheid",
    "unit_price": "Eenheidsprijs",
    "discount": "Korting",
    "paid_invoices": "Betaalde facturen",
    "open_invoices": "Open facturen",
    "to": "de",
    "paid": "betaald",
    "not_paid": "Niet betaald",
    "OK": "OK",
    "invoice_no": "Factuurnr",
    "from": "van",
    "at": "naar",
    "email": "e-mail",
    "phone": "telefoon",
    "VAT": "BTW",
    "VAT_number": "Btw-nummer",
    "facebook_page": "Facebook-pagina",
    "likedin_page": "Linkedin-pagina",
    "paid_by_the_customer": "Betaald door de klant",
    "remarks": "Opmerkingen",
    "payment_history": "Betalingsgeschiedenis",
    "method_of_payment": "Betaalmethode",
    "amount": "bedrag",
    "the_rates": "de tarieven",
    "all_the_tariffs_for_the_care": "Alle tarieven van uw salons. Neem contact op met een beheerder als het protocol niet bestaat.",
    "protocols_of_care": "Protocollen van zorg",
    "products_and_other services": "Producten en andere diensten",
    "products_included": "Producten inbegrepen",
    "price": "prijs",
    "protocols": "protocollen",
    "protocol": "protocol",
    "care": "zorg",
    "name_of_care": "Naam van de behandeling",
    "care_price": "Prijs van de zorg",
    "here_description": "Geef hier de beschrijving aan",
    "add_a_rate": "Voeg een tarief toe",
    "product": "product",
    "find_the_protocols": "Zoek de protocollen Celestetic en de jouwe",
    "find_the_technologies": "Zoek de technologieën van Celestetic",
    "create_this_new_technology": "Maak deze nieuwe technologie",
    "name_of_new_technology": "Naam van de nieuwe technologie",
    "new_technology": "Nieuwe technologie",
    "technology_photos": "Foto&#39;s van technologie",
    "add_new_photos": "Voeg nieuwe foto&#39;s toe",
    "name_of_the_technology": "Naam van de technologie",
    "details": "gegevens",
    "variations": "variaties",
    "insert_variants_and_link_technologies": "Voeg varianten en link-technologieën toe aan elke variant",
    "meeting": "sessie",
    "autofill": "Autofill",
    "add_a_variation": "Voeg een variatie toe",
    "insert_here_settings": "Voer hier de instellingen in",
    "del_settings": "Verwijder instellingen",
    "save_changes": "Sla wijzigingen op",
    "feedback_title": "Feedback / Post Care vragenlijsten",
    "feedback_subtitle": "De vragenlijst die verschijnt uit de tweede sessie met betrekking tot de vorige sessie.",
    "feedback_name": "Naam van de feedbackvragenlijst",
    "create_this_new_feedback": "Maak deze nieuwe vragenlijst",
    "new_feedback": "Nieuwe feedback",
    "emails_title": "E-mailsjablonen",
    "new_template": "Nieuwe sjabloon",
    "emails_subtitle": "Email upsell / cross-sell e-mailsjabloon en herinneringen. Deze e-mail werd na de behandelingen naar klanten gestuurd om te praten over de opties voor cross sell / upsell",
    "email_template_name": "Naam van de e-mailsjabloon",
    "email_subject": "Onderwerp van de e-mail",
    "time_to_send": "Verzonden na hoe lang",
    "day": "dag",
    "days": "dagen",
    "week": "week",
    "weeks": "weken",
    "write_email": "Schrijf de e-mail",
    "create_this_template": "Maak deze nieuwe sjabloon",
    "rooms_number": "Aantal kamer (s)",
    "parlor_language": "Taal van de salon",
    "discharge_title": "Formulier voor vrijgave / geïnformeerde toestemming",
    "new_discharge": "Nieuwe stortplaats",
    "discharges_subtitle": "Dit formulier is noodzakelijk voor sommige behandelingen en wordt na ondertekening automatisch per e-mail verzonden). De te lezen tekst moet met een vinger op de tablet worden ondertekend.",
    "discharge_template_name": "titel van de kwijting",
    "write_discharge": "Schrijf hier de te lezen tekst",
    "create_this_discharge": "Maak deze nieuwe tip",
    "postcares_title": "Post-processingprotocollen",
    "postcares_subtitle": "Deze tekst wordt aan het einde van de behandeling automatisch per e-mail aan de klant verzonden.",
    "new_postcare": "Nieuw protocol",
    "postcares_name": "Naam van de sjabloon voor het nabewerkingsprotocol",
    "write_postcare": "Schrijf de postcare",
    "create_this_new_postcare": "Maak dit nieuwe protocol",
    "postcare_template_name": "Naam van de sjabloon voor het nabewerkingsprotocol",
    "taglist_title": "Zorg Tags",
    "taglist_subtitle": "Bewerk de tags van de zorgprotocollen",
    "tag_variation": "Variatie Tag",
    "tag_option": "Optie Tag",
    "add_a_tag": "Voeg een tag toe",
    "tag_name": "Tag naam",
    "parlors_title": "de instituten",
    "parlors_subtitle": "U hebt alleen toegang tot de instellingen waaraan u verbonden bent. Neem contact op met een beheerder als uw instituut er niet is",
    "create_new_institut": "Maak een nieuw instituut",
    "CGV_title": "Voorwaarden",
    "CGV_subtitle": "Algemene verkoopvoorwaarden",
    "users_title": "Alle gebruikers van de app",
    "users_subtitle": "Alleen gebruikers met de beheerdersstatus hebben toegang tot deze pagina",
    "all_customers": "Alle klanten van uw salons",
    "export_xls": "Exporteer als .xls",
    "add_a_question": "Voeg een vraag toe",
    "create_this_new_anamnese": "Maak deze nieuwe anamnese",
    "document_submitted_to": "Document ingediend bij",
    "client_has_not_yet_signed_the_release": "De klant heeft de kwijting nog niet ondertekend",
    "if_the_answer_is_yes_further_processing_cannot_be_carried_out": "In het geval van een &quot;Ja&quot; -antwoord kan verdere verwerking niet plaatsvinden",
    "the_client_has_not_yet_answered_the_history": "De klant heeft de anamnese nog niet beantwoord",
    "client_has_not_yet_signed_the_history": "De klant heeft de anamnese nog niet ondertekend",
    "customer_has_not_yet_responded_to_the_feedback": "Klant heeft nog niet op feedback gereageerd",
    "photos_at_the_beginning_of_the_session": "Begin van sessiefoto&#39;s",
    "there_are_no_photos_for_the_beginning_of_this_session": "Er zijn geen foto&#39;s voor het begin van deze sessie",
    "photos_at_the_end_of_the_session": "Einde sessie foto&#39;s",
    "there_are_no_pictures_for_the_end_of_this_session": "Er zijn geen foto&#39;s aan het einde van deze sessie",
    "linked_institut": "Geassocieerde instituten",
    "status": "staat",
    "anamnese_name": "Naam van de anamnese",
    "discharge_name": "Naam van de kwijting",
    "template_name": "E-mailsjabloonnaam",
    "institute_name": "Beurs naam",
    "manageress": "directrice",
    "staff_name": "Naam van schoonheidsspecialisten",
    "manageress_name": "Naam van de manager",
    "add_a_manager": "Voeg een manager toe",
    "add_staff_to_team": "Voeg een lid toe aan het team",
    "team": "het team",
    "create_a_new_institute": "Maak een nieuw instituut",
    "name_of_new_institute": "Naam van het nieuwe instituut",
    "Manager": "manager",
    "Employee": "werknemer",
    "Admin": "administrateur",
    "user_management": "Gebruikersbeheer",
    "linked_instituts": "Bijgevoegde centra (om een ​​centrum te linken, ga naar de middelste kaart)",
    "current_lang": "Nederlands",
    "english": "Engels",
    "french": "Frans",
    "dutch": "Nederlands"
}